gt_lib/__init__.py
gt_lib/atr.py
gt_lib/bollinger_band.py
gt_lib/donchian_channel.py
gt_lib/double_ema.py
gt_lib/ease_of_movement.py
gt_lib/ema.py
gt_lib/ema_crossover.py
gt_lib/fractal.py
gt_lib/hull_moving_avg.py
gt_lib/ichimoku_cloud.py
gt_lib/macd.py
gt_lib/money_flow_index.py
gt_lib/period_high.py
gt_lib/period_low.py
gt_lib/reversal.py
gt_lib/rsi.py
gt_lib/sma.py
gt_lib/stochastic_rsi.py
gt_lib/trailing_stop_loss.py
gt_lib/volatility.py
gt_lib/weighted_moving_average.py
gt_lib-0.1.4.dist-info/LICENSE
gt_lib-0.1.4.dist-info/METADATA
gt_lib-0.1.4.dist-info/WHEEL
gt_lib-0.1.4.dist-info/top_level.txt
gt_lib-0.1.4.dist-info/RECORD
