Metadata-Version: 2.1
Name: gt-lib
Version: 0.1.4
Summary: talib library
Home-page: https://github.com/pypa/sampleproject
Author: danish khajuria
Author-email: danishkhajuria@gmail.com
License: UNKNOWN
Project-URL: Bug Tracker, https://github.com/pypa/sampleproject/issues
Platform: UNKNOWN
Classifier: Programming Language :: Python :: 3
Classifier: License :: OSI Approved :: MIT License
Classifier: Operating System :: OS Independent
Requires-Python: >=3.6
